saiesgreet/__init__.py
saiesgreet/core.py
saiesgreet-0.1.0.dist-info/licenses/LICENSE
saiesgreet-0.1.0.dist-info/METADATA
saiesgreet-0.1.0.dist-info/WHEEL
saiesgreet-0.1.0.dist-info/top_level.txt
saiesgreet-0.1.0.dist-info/RECORD
