Metadata-Version: 2.4
Name: saiesgreet
Version: 0.1.0
Summary: A tiny Python package to greet people.
Author-email: Tejeswini <pathivada142@gmail.com>
License: MIT
Requires-Python: >=3.7
License-File: LICENSE
Dynamic: license-file
